{
  "swagger": "2.0",
  "info": {
    "title": "DHo's API",
    "description": "API for an ecommerce app",
    "version": "1.0.0"
  },
  "host": "",
  "basePath": "/",
  "schemes": [],
  "paths": {
    "/": {
      "get": {
        "description": "",
        "responses": {
          "200": {
            "description": "OK"
          }
        }
      }
    },
    "/api-update": {
      "get": {
        "tags": [
          "test"
        ],
        "description": "",
        "responses": {
          "200": {
            "description": "OK"
          }
        }
      }
    },
    "/auth/sign-in": {
      "post": {
        "tags": [
          "Auth"
        ],
        "description": "",
        "parameters": [
          {
            "name": "obj",
            "in": "body",
            "description": "data input to login",
            "required": true,
            "schema": {
              "type": "object",
              "properties": {
                "phone": {
                  "type": "string",
                  "example": "0123456789"
                },
                "password": {
                  "type": "string",
                  "example": "123456"
                }
              }
            }
          }
        ],
        "responses": {
          "200": {
            "description": "OK"
          },
          "401": {
            "description": "Unauthorized"
          },
          "422": {
            "description": "Unprocessable Entity"
          },
          "500": {
            "description": "Internal Server Error"
          }
        }
      }
    },
    "/auth/sign-up": {
      "post": {
        "tags": [
          "Auth"
        ],
        "description": "",
        "parameters": [
          {
            "name": "body",
            "in": "body",
            "schema": {
              "type": "object",
              "properties": {
                "phone": {
                  "example": "any"
                },
                "email": {
                  "example": "any"
                },
                "password": {
                  "example": "any"
                },
                "password_confirm": {
                  "example": "any"
                }
              }
            }
          }
        ],
        "responses": {
          "200": {
            "description": "OK"
          },
          "409": {
            "description": "Conflict"
          },
          "422": {
            "description": "Unprocessable Entity"
          },
          "500": {
            "description": "Internal Server Error"
          }
        }
      }
    },
    "/auth/test-auth": {
      "get": {
        "tags": [
          "Auth"
        ],
        "description": "",
        "parameters": [
          {
            "name": "Authorization",
            "in": "header",
            "type": "string"
          }
        ],
        "responses": {
          "200": {
            "description": "OK"
          },
          "400": {
            "description": "Bad Request"
          },
          "401": {
            "description": "Unauthorized"
          }
        }
      }
    },
    "/auth/forgot-password": {
      "post": {
        "tags": [
          "Auth"
        ],
        "description": "",
        "parameters": [
          {
            "name": "body",
            "in": "body",
            "schema": {
              "type": "object",
              "properties": {
                "email": {
                  "example": "any"
                }
              }
            }
          }
        ],
        "responses": {
          "200": {
            "description": "OK"
          }
        }
      }
    },
    "/location/province": {
      "get": {
        "tags": [
          "location"
        ],
        "description": "",
        "responses": {
          "200": {
            "description": "OK"
          },
          "500": {
            "description": "Internal Server Error"
          }
        }
      }
    },
    "/location/district/{province_id}": {
      "get": {
        "tags": [
          "location"
        ],
        "description": "",
        "parameters": [
          {
            "name": "province_id",
            "in": "path",
            "required": true,
            "type": "string"
          }
        ],
        "responses": {
          "200": {
            "description": "OK"
          },
          "500": {
            "description": "Internal Server Error"
          }
        }
      }
    },
    "/location/districts": {
      "post": {
        "tags": [
          "location"
        ],
        "description": "",
        "parameters": [
          {
            "name": "body",
            "in": "body",
            "schema": {
              "type": "object",
              "properties": {
                "province_id": {
                  "example": "any"
                },
                "district_id": {
                  "example": "any"
                }
              }
            }
          }
        ],
        "responses": {
          "200": {
            "description": "OK"
          },
          "500": {
            "description": "Internal Server Error"
          }
        }
      }
    },
    "/search": {
      "get": {
        "tags": [
          "Posts"
        ],
        "description": "",
        "parameters": [
          {
            "name": "q",
            "in": "query",
            "type": "string"
          },
          {
            "name": "page",
            "in": "query",
            "type": "string"
          },
          {
            "name": "Authorization",
            "in": "header",
            "type": "string"
          }
        ],
        "responses": {
          "200": {
            "description": "OK"
          },
          "400": {
            "description": "Bad Request"
          },
          "500": {
            "description": "Internal Server Error"
          }
        }
      }
    },
    "/posts": {
      "get": {
        "tags": [
          "Posts"
        ],
        "description": "",
        "parameters": [
          {
            "name": "Authorization",
            "in": "header",
            "type": "string"
          },
          {
            "name": "sortBy",
            "in": "query",
            "type": "string"
          },
          {
            "name": "condition",
            "in": "query",
            "type": "string"
          },
          {
            "name": "brand",
            "in": "query",
            "type": "string"
          },
          {
            "name": "engine",
            "in": "query",
            "type": "string"
          },
          {
            "name": "size",
            "in": "query",
            "type": "string"
          },
          {
            "name": "priceRange",
            "in": "query",
            "type": "string"
          },
          {
            "name": "page",
            "in": "query",
            "type": "string"
          }
        ],
        "responses": {
          "200": {
            "description": "OK"
          },
          "400": {
            "description": "Bad Request"
          },
          "500": {
            "description": "Internal Server Error"
          }
        }
      },
      "post": {
        "tags": [
          "Posts"
        ],
        "description": "",
        "parameters": [
          {
            "name": "Authorization",
            "in": "header",
            "type": "string"
          },
          {
            "name": "body",
            "in": "body",
            "schema": {
              "type": "object",
              "properties": {
                "post_id": {
                  "example": "any"
                }
              }
            }
          }
        ],
        "responses": {
          "200": {
            "description": "OK"
          },
          "404": {
            "description": "Not Found"
          },
          "500": {
            "description": "Internal Server Error"
          }
        }
      }
    },
    "/posts/upload": {
      "post": {
        "tags": [
          "Posts"
        ],
        "description": "",
        "parameters": [
          {
            "name": "Authorization",
            "in": "header",
            "type": "string"
          },
          {
            "name": "obj",
            "in": "body",
            "schema": {
              "type": "object",
              "properties": {
                "name": {
                  "example": "any"
                },
                "price": {
                  "example": "any"
                },
                "images": {
                  "example": "any"
                },
                "case_size": {
                  "example": "any"
                },
                "rest": {
                  "example": "any"
                }
              }
            },
            "description": "If the image is not in base64, BE will handle it and add the tag\n Allowed params:\nname,\ndescription,\nprice,\nstatus,\nbrand,\norigin,\ncase_size,\ncolor,\nstrap_color,\nstrap_material,\nbattery_life,\nwaterproof,\npower,\nengine,\nimages,\ngender\n ",
            "required": true
          }
        ],
        "responses": {
          "201": {
            "description": "Created"
          },
          "400": {
            "description": "Bad Request"
          },
          "401": {
            "description": "Unauthorized"
          },
          "403": {
            "description": "Forbidden"
          },
          "500": {
            "description": "Internal Server Error"
          }
        }
      }
    },
    "/users": {
      "get": {
        "tags": [
          "User"
        ],
        "description": "dùng lấy profile của user",
        "parameters": [
          {
            "name": "Authorization",
            "in": "header",
            "type": "string"
          }
        ],
        "responses": {
          "200": {
            "description": "OK"
          },
          "400": {
            "description": "Bad Request"
          },
          "401": {
            "description": "Unauthorized"
          },
          "500": {
            "description": "Internal Server Error"
          }
        }
      },
      "post": {
        "tags": [
          "User"
        ],
        "description": "dùng sửa profile của user",
        "parameters": [
          {
            "name": "Authorization",
            "in": "header",
            "type": "string"
          },
          {
            "name": "obj",
            "in": "body",
            "schema": {
              "type": "object",
              "properties": {
                "avatar": {
                  "example": "any"
                },
                "rest": {
                  "example": "any"
                }
              }
            },
            "description": " avatar must be in base64, \n Allowed params:\nlast_name,\nfirst_name,\nphone,\nemail,\navatar,\n",
            "required": true
          }
        ],
        "responses": {
          "200": {
            "description": "OK"
          },
          "400": {
            "description": "Bad Request"
          },
          "401": {
            "description": "Unauthorized"
          },
          "500": {
            "description": "Internal Server Error"
          }
        }
      }
    },
    "/users/address": {
      "get": {
        "tags": [
          "User"
        ],
        "description": "dùng lấy address của user",
        "parameters": [
          {
            "name": "Authorization",
            "in": "header",
            "type": "string"
          }
        ],
        "responses": {
          "200": {
            "description": "OK"
          },
          "400": {
            "description": "Bad Request"
          },
          "401": {
            "description": "Unauthorized"
          },
          "500": {
            "description": "Internal Server Error"
          }
        }
      }
    },
    "/users/address/{id}": {
      "put": {
        "tags": [
          "User"
        ],
        "description": "dùng chỉnh address của user, is default gồm 0 và 1",
        "parameters": [
          {
            "name": "id",
            "in": "path",
            "required": true,
            "type": "string"
          },
          {
            "name": "Authorization",
            "in": "header",
            "type": "string"
          },
          {
            "name": "body",
            "in": "body",
            "schema": {
              "type": "object",
              "properties": {
                "is_default": {
                  "example": "any"
                },
                "first_name": {
                  "example": "any"
                },
                "last_name": {
                  "example": "any"
                },
                "phone_number": {
                  "example": "any"
                },
                "street": {
                  "example": "any"
                },
                "province_id": {
                  "example": "any"
                },
                "district_id": {
                  "example": "any"
                },
                "ward_id": {
                  "example": "any"
                }
              }
            }
          }
        ],
        "responses": {
          "200": {
            "description": "OK"
          },
          "400": {
            "description": "Bad Request"
          },
          "401": {
            "description": "Unauthorized"
          },
          "404": {
            "description": "Not Found"
          },
          "500": {
            "description": "Internal Server Error"
          }
        }
      },
      "delete": {
        "tags": [
          "User"
        ],
        "description": "",
        "parameters": [
          {
            "name": "id",
            "in": "path",
            "required": true,
            "type": "string"
          },
          {
            "name": "Authorization",
            "in": "header",
            "type": "string"
          }
        ],
        "responses": {
          "200": {
            "description": "OK"
          },
          "400": {
            "description": "Bad Request"
          },
          "401": {
            "description": "Unauthorized"
          },
          "404": {
            "description": "Not Found"
          },
          "500": {
            "description": "Internal Server Error"
          }
        }
      }
    },
    "/users/address/": {
      "post": {
        "tags": [
          "User"
        ],
        "description": "dùng thêm address cho user, is default gồm 0 và 1",
        "parameters": [
          {
            "name": "Authorization",
            "in": "header",
            "type": "string"
          },
          {
            "name": "body",
            "in": "body",
            "schema": {
              "type": "object",
              "properties": {
                "is_default": {
                  "example": "any"
                },
                "first_name": {
                  "example": "any"
                },
                "last_name": {
                  "example": "any"
                },
                "phone_number": {
                  "example": "any"
                },
                "street": {
                  "example": "any"
                },
                "province_id": {
                  "example": "any"
                },
                "district_id": {
                  "example": "any"
                },
                "ward_id": {
                  "example": "any"
                }
              }
            }
          }
        ],
        "responses": {
          "200": {
            "description": "OK"
          },
          "400": {
            "description": "Bad Request"
          },
          "401": {
            "description": "Unauthorized"
          },
          "404": {
            "description": "Not Found"
          },
          "500": {
            "description": "Internal Server Error"
          }
        }
      }
    },
    "/users/status": {
      "get": {
        "tags": [
          "User"
        ],
        "description": "dùng lấy status seller của user",
        "parameters": [
          {
            "name": "Authorization",
            "in": "header",
            "type": "string"
          }
        ],
        "responses": {
          "200": {
            "description": "OK"
          },
          "400": {
            "description": "Bad Request"
          },
          "401": {
            "description": "Unauthorized"
          },
          "404": {
            "description": "Not Found"
          },
          "500": {
            "description": "Internal Server Error"
          }
        }
      }
    },
    "/users/change-password": {
      "post": {
        "tags": [
          "User"
        ],
        "description": "dùng lấy đổi password",
        "parameters": [
          {
            "name": "Authorization",
            "in": "header",
            "type": "string"
          },
          {
            "name": "body",
            "in": "body",
            "schema": {
              "type": "object",
              "properties": {
                "oldPassword": {
                  "example": "any"
                },
                "newPassword": {
                  "example": "any"
                },
                "confirmPassword": {
                  "example": "any"
                }
              }
            }
          }
        ],
        "responses": {
          "200": {
            "description": "OK"
          },
          "400": {
            "description": "Bad Request"
          },
          "401": {
            "description": "Unauthorized"
          },
          "404": {
            "description": "Not Found"
          }
        }
      }
    },
    "/favorite_post": {
      "get": {
        "tags": [
          "Favorite post"
        ],
        "description": "",
        "parameters": [
          {
            "name": "Authorization",
            "in": "header",
            "type": "string"
          }
        ],
        "responses": {
          "200": {
            "description": "OK"
          },
          "400": {
            "description": "Bad Request"
          },
          "401": {
            "description": "Unauthorized"
          },
          "500": {
            "description": "Internal Server Error"
          }
        }
      },
      "post": {
        "tags": [
          "Favorite post"
        ],
        "description": "",
        "parameters": [
          {
            "name": "Authorization",
            "in": "header",
            "type": "string"
          },
          {
            "name": "body",
            "in": "body",
            "schema": {
              "type": "object",
              "properties": {
                "post_id": {
                  "example": "any"
                }
              }
            }
          }
        ],
        "responses": {
          "201": {
            "description": "Created"
          },
          "400": {
            "description": "Bad Request"
          },
          "401": {
            "description": "Unauthorized"
          },
          "500": {
            "description": "Internal Server Error"
          }
        }
      }
    },
    "/favorite_post/{id}": {
      "delete": {
        "tags": [
          "Favorite post"
        ],
        "description": "",
        "parameters": [
          {
            "name": "id",
            "in": "path",
            "required": true,
            "type": "string"
          },
          {
            "name": "Authorization",
            "in": "header",
            "type": "string"
          }
        ],
        "responses": {
          "200": {
            "description": "OK"
          },
          "400": {
            "description": "Bad Request"
          },
          "401": {
            "description": "Unauthorized"
          },
          "404": {
            "description": "Not Found"
          },
          "500": {
            "description": "Internal Server Error"
          }
        }
      }
    }
  }
}